{"nodes": [{"id": "kalachakra_engine", "label": "kalachakra_engine.py", "file_type": "code", "source_file": "app/kalachakra_engine.py", "source_location": "L1"}, {"id": "kalachakra_engine_navamsa_rashi_index", "label": "_navamsa_rashi_index()", "file_type": "code", "source_file": "app/kalachakra_engine.py", "source_location": "L89"}, {"id": "kalachakra_engine_is_savya", "label": "_is_savya()", "file_type": "code", "source_file": "app/kalachakra_engine.py", "source_location": "L125"}, {"id": "kalachakra_engine_build_sign_sequence", "label": "_build_sign_sequence()", "file_type": "code", "source_file": "app/kalachakra_engine.py", "source_location": "L144"}, {"id": "kalachakra_engine_assign_deha_jeeva", "label": "_assign_deha_jeeva()", "file_type": "code", "source_file": "app/kalachakra_engine.py", "source_location": "L167"}, {"id": "kalachakra_engine_find_deha_jeeva_rashis", "label": "_find_deha_jeeva_rashis()", "file_type": "code", "source_file": "app/kalachakra_engine.py", "source_location": "L176"}, {"id": "kalachakra_engine_calculate_balance", "label": "_calculate_balance()", "file_type": "code", "source_file": "app/kalachakra_engine.py", "source_location": "L190"}, {"id": "kalachakra_engine_moon_nakshatra_pada", "label": "_moon_nakshatra_pada()", "file_type": "code", "source_file": "app/kalachakra_engine.py", "source_location": "L224"}, {"id": "kalachakra_engine_parse_date", "label": "_parse_date()", "file_type": "code", "source_file": "app/kalachakra_engine.py", "source_location": "L242"}, {"id": "kalachakra_engine_add_years", "label": "_add_years()", "file_type": "code", "source_file": "app/kalachakra_engine.py", "source_location": "L247"}, {"id": "kalachakra_engine_calculate_kalachakra_dasha", "label": "calculate_kalachakra_dasha()", "file_type": "code", "source_file": "app/kalachakra_engine.py", "source_location": "L256"}, {"id": "kalachakra_engine_rationale_1", "label": "kalachakra_engine.py \u2014 Kalachakra Dasha Calculation Engine =====================", "file_type": "rationale", "source_file": "app/kalachakra_engine.py", "source_location": "L1"}, {"id": "kalachakra_engine_rationale_90", "label": "Return the zodiac index (0-11) of the navamsa rashi for a given     nakshatra-pa", "file_type": "rationale", "source_file": "app/kalachakra_engine.py", "source_location": "L90"}, {"id": "kalachakra_engine_rationale_126", "label": "Return True if the given nakshatra-pada follows the Savya (clockwise)     path,", "file_type": "rationale", "source_file": "app/kalachakra_engine.py", "source_location": "L126"}, {"id": "kalachakra_engine_rationale_145", "label": "Build the 9-sign dasha half-cycle starting from *start_rashi_index*.      Classi", "file_type": "rationale", "source_file": "app/kalachakra_engine.py", "source_location": "L145"}, {"id": "kalachakra_engine_rationale_168", "label": "Return a list of 'Deha' / 'Jeeva' labels for each sign in *sequence*.      Class", "file_type": "rationale", "source_file": "app/kalachakra_engine.py", "source_location": "L168"}, {"id": "kalachakra_engine_rationale_179", "label": "Return the (deha_rashi, jeeva_rashi) \u2014 the first sign labelled Deha     and the", "file_type": "rationale", "source_file": "app/kalachakra_engine.py", "source_location": "L179"}, {"id": "kalachakra_engine_rationale_191", "label": "Calculate the remaining fraction of the first dasha period at birth.      The Mo", "file_type": "rationale", "source_file": "app/kalachakra_engine.py", "source_location": "L191"}, {"id": "kalachakra_engine_rationale_225", "label": "Return (nak_index, pada_index, nak_name, pada_number_1based) from     the Moon's", "file_type": "rationale", "source_file": "app/kalachakra_engine.py", "source_location": "L225"}, {"id": "kalachakra_engine_rationale_243", "label": "Parse YYYY-MM-DD date string.", "file_type": "rationale", "source_file": "app/kalachakra_engine.py", "source_location": "L243"}, {"id": "kalachakra_engine_rationale_248", "label": "Add fractional years to a datetime using 365.25 days/year.", "file_type": "rationale", "source_file": "app/kalachakra_engine.py", "source_location": "L248"}, {"id": "kalachakra_engine_rationale_261", "label": "Calculate Kalachakra Dasha periods.      The Kalachakra Dasha is a rashi-based n", "file_type": "rationale", "source_file": "app/kalachakra_engine.py", "source_location": "L261"}], "edges": [{"source": "kalachakra_engine", "target": "datetime", "relation": "imports_from", "confidence": "EXTRACTED", "source_file": "app/kalachakra_engine.py", "source_location": "L22", "weight": 1.0}, {"source": "kalachakra_engine", "target": "typing", "relation": "imports_from", "confidence": "EXTRACTED", "source_file": "app/kalachakra_engine.py", "source_location": "L23", "weight": 1.0}, {"source": "kalachakra_engine", "target": "kalachakra_engine_navamsa_rashi_index", "relation": "contains", "confidence": "EXTRACTED", "source_file": "app/kalachakra_engine.py", "source_location": "L89", "weight": 1.0}, {"source": "kalachakra_engine", "target": "kalachakra_engine_is_savya", "relation": "contains", "confidence": "EXTRACTED", "source_file": "app/kalachakra_engine.py", "source_location": "L125", "weight": 1.0}, {"source": "kalachakra_engine", "target": "kalachakra_engine_build_sign_sequence", "relation": "contains", "confidence": "EXTRACTED", "source_file": "app/kalachakra_engine.py", "source_location": "L144", "weight": 1.0}, {"source": "kalachakra_engine", "target": "kalachakra_engine_assign_deha_jeeva", "relation": "contains", "confidence": "EXTRACTED", "source_file": "app/kalachakra_engine.py", "source_location": "L167", "weight": 1.0}, {"source": "kalachakra_engine", "target": "kalachakra_engine_find_deha_jeeva_rashis", "relation": "contains", "confidence": "EXTRACTED", "source_file": "app/kalachakra_engine.py", "source_location": "L176", "weight": 1.0}, {"source": "kalachakra_engine", "target": "kalachakra_engine_calculate_balance", "relation": "contains", "confidence": "EXTRACTED", "source_file": "app/kalachakra_engine.py", "source_location": "L190", "weight": 1.0}, {"source": "kalachakra_engine", "target": "kalachakra_engine_moon_nakshatra_pada", "relation": "contains", "confidence": "EXTRACTED", "source_file": "app/kalachakra_engine.py", "source_location": "L224", "weight": 1.0}, {"source": "kalachakra_engine", "target": "kalachakra_engine_parse_date", "relation": "contains", "confidence": "EXTRACTED", "source_file": "app/kalachakra_engine.py", "source_location": "L242", "weight": 1.0}, {"source": "kalachakra_engine", "target": "kalachakra_engine_add_years", "relation": "contains", "confidence": "EXTRACTED", "source_file": "app/kalachakra_engine.py", "source_location": "L247", "weight": 1.0}, {"source": "kalachakra_engine", "target": "kalachakra_engine_calculate_kalachakra_dasha", "relation": "contains", "confidence": "EXTRACTED", "source_file": "app/kalachakra_engine.py", "source_location": "L256", "weight": 1.0}, {"source": "kalachakra_engine_calculate_kalachakra_dasha", "target": "kalachakra_engine_moon_nakshatra_pada", "relation": "calls", "confidence": "EXTRACTED", "source_file": "app/kalachakra_engine.py", "source_location": "L287", "weight": 1.0}, {"source": "kalachakra_engine_calculate_kalachakra_dasha", "target": "kalachakra_engine_navamsa_rashi_index", "relation": "calls", "confidence": "EXTRACTED", "source_file": "app/kalachakra_engine.py", "source_location": "L290", "weight": 1.0}, {"source": "kalachakra_engine_calculate_kalachakra_dasha", "target": "kalachakra_engine_is_savya", "relation": "calls", "confidence": "EXTRACTED", "source_file": "app/kalachakra_engine.py", "source_location": "L294", "weight": 1.0}, {"source": "kalachakra_engine_calculate_kalachakra_dasha", "target": "kalachakra_engine_build_sign_sequence", "relation": "calls", "confidence": "EXTRACTED", "source_file": "app/kalachakra_engine.py", "source_location": "L298", "weight": 1.0}, {"source": "kalachakra_engine_calculate_kalachakra_dasha", "target": "kalachakra_engine_assign_deha_jeeva", "relation": "calls", "confidence": "EXTRACTED", "source_file": "app/kalachakra_engine.py", "source_location": "L299", "weight": 1.0}, {"source": "kalachakra_engine_calculate_kalachakra_dasha", "target": "kalachakra_engine_find_deha_jeeva_rashis", "relation": "calls", "confidence": "EXTRACTED", "source_file": "app/kalachakra_engine.py", "source_location": "L300", "weight": 1.0}, {"source": "kalachakra_engine_calculate_kalachakra_dasha", "target": "kalachakra_engine_calculate_balance", "relation": "calls", "confidence": "EXTRACTED", "source_file": "app/kalachakra_engine.py", "source_location": "L303", "weight": 1.0}, {"source": "kalachakra_engine_calculate_kalachakra_dasha", "target": "kalachakra_engine_parse_date", "relation": "calls", "confidence": "EXTRACTED", "source_file": "app/kalachakra_engine.py", "source_location": "L308", "weight": 1.0}, {"source": "kalachakra_engine_calculate_kalachakra_dasha", "target": "kalachakra_engine_add_years", "relation": "calls", "confidence": "EXTRACTED", "source_file": "app/kalachakra_engine.py", "source_location": "L313", "weight": 1.0}, {"source": "kalachakra_engine_rationale_1", "target": "kalachakra_engine", "relation": "rationale_for", "confidence": "EXTRACTED", "source_file": "app/kalachakra_engine.py", "source_location": "L1", "weight": 1.0}, {"source": "kalachakra_engine_rationale_90", "target": "kalachakra_engine_navamsa_rashi_index", "relation": "rationale_for", "confidence": "EXTRACTED", "source_file": "app/kalachakra_engine.py", "source_location": "L90", "weight": 1.0}, {"source": "kalachakra_engine_rationale_126", "target": "kalachakra_engine_is_savya", "relation": "rationale_for", "confidence": "EXTRACTED", "source_file": "app/kalachakra_engine.py", "source_location": "L126", "weight": 1.0}, {"source": "kalachakra_engine_rationale_145", "target": "kalachakra_engine_build_sign_sequence", "relation": "rationale_for", "confidence": "EXTRACTED", "source_file": "app/kalachakra_engine.py", "source_location": "L145", "weight": 1.0}, {"source": "kalachakra_engine_rationale_168", "target": "kalachakra_engine_assign_deha_jeeva", "relation": "rationale_for", "confidence": "EXTRACTED", "source_file": "app/kalachakra_engine.py", "source_location": "L168", "weight": 1.0}, {"source": "kalachakra_engine_rationale_179", "target": "kalachakra_engine_find_deha_jeeva_rashis", "relation": "rationale_for", "confidence": "EXTRACTED", "source_file": "app/kalachakra_engine.py", "source_location": "L179", "weight": 1.0}, {"source": "kalachakra_engine_rationale_191", "target": "kalachakra_engine_calculate_balance", "relation": "rationale_for", "confidence": "EXTRACTED", "source_file": "app/kalachakra_engine.py", "source_location": "L191", "weight": 1.0}, {"source": "kalachakra_engine_rationale_225", "target": "kalachakra_engine_moon_nakshatra_pada", "relation": "rationale_for", "confidence": "EXTRACTED", "source_file": "app/kalachakra_engine.py", "source_location": "L225", "weight": 1.0}, {"source": "kalachakra_engine_rationale_243", "target": "kalachakra_engine_parse_date", "relation": "rationale_for", "confidence": "EXTRACTED", "source_file": "app/kalachakra_engine.py", "source_location": "L243", "weight": 1.0}, {"source": "kalachakra_engine_rationale_248", "target": "kalachakra_engine_add_years", "relation": "rationale_for", "confidence": "EXTRACTED", "source_file": "app/kalachakra_engine.py", "source_location": "L248", "weight": 1.0}, {"source": "kalachakra_engine_rationale_261", "target": "kalachakra_engine_calculate_kalachakra_dasha", "relation": "rationale_for", "confidence": "EXTRACTED", "source_file": "app/kalachakra_engine.py", "source_location": "L261", "weight": 1.0}]}