{"nodes": [{"id": "gochara_vedha_engine", "label": "gochara_vedha_engine.py", "file_type": "code", "source_file": "app/gochara_vedha_engine.py", "source_location": "L1"}, {"id": "gochara_vedha_engine_load_vedha_table", "label": "load_vedha_table()", "file_type": "code", "source_file": "app/gochara_vedha_engine.py", "source_location": "L44"}, {"id": "gochara_vedha_engine_load_latta_table", "label": "load_latta_table()", "file_type": "code", "source_file": "app/gochara_vedha_engine.py", "source_location": "L52"}, {"id": "gochara_vedha_engine_house_from_moon", "label": "_house_from_moon()", "file_type": "code", "source_file": "app/gochara_vedha_engine.py", "source_location": "L64"}, {"id": "gochara_vedha_engine_nakshatra_from_longitude", "label": "_nakshatra_from_longitude()", "file_type": "code", "source_file": "app/gochara_vedha_engine.py", "source_location": "L74"}, {"id": "gochara_vedha_engine_nakshatra_distance", "label": "_nakshatra_distance()", "file_type": "code", "source_file": "app/gochara_vedha_engine.py", "source_location": "L84"}, {"id": "gochara_vedha_engine_is_exception_pair", "label": "_is_exception_pair()", "file_type": "code", "source_file": "app/gochara_vedha_engine.py", "source_location": "L94"}, {"id": "gochara_vedha_engine_apply_vedhas", "label": "apply_vedhas()", "file_type": "code", "source_file": "app/gochara_vedha_engine.py", "source_location": "L105"}, {"id": "gochara_vedha_engine_apply_lattas", "label": "apply_lattas()", "file_type": "code", "source_file": "app/gochara_vedha_engine.py", "source_location": "L198"}, {"id": "gochara_vedha_engine_enrich_transits", "label": "enrich_transits()", "file_type": "code", "source_file": "app/gochara_vedha_engine.py", "source_location": "L278"}, {"id": "gochara_vedha_engine_rationale_1", "label": "gochara_vedha_engine.py \u2014 Gochara Vedha + Latta Analysis =======================", "file_type": "rationale", "source_file": "app/gochara_vedha_engine.py", "source_location": "L1"}, {"id": "gochara_vedha_engine_rationale_65", "label": "Return house number (1-12) of transit_sign counted from moon_sign.     House 1 =", "file_type": "rationale", "source_file": "app/gochara_vedha_engine.py", "source_location": "L65"}, {"id": "gochara_vedha_engine_rationale_75", "label": "Return nakshatra name for an absolute longitude 0-360.", "file_type": "rationale", "source_file": "app/gochara_vedha_engine.py", "source_location": "L75"}, {"id": "gochara_vedha_engine_rationale_85", "label": "Count forward distance in nakshatras (1-based) from `from_nak` to `to_nak`.", "file_type": "rationale", "source_file": "app/gochara_vedha_engine.py", "source_location": "L85"}, {"id": "gochara_vedha_engine_rationale_95", "label": "Check if these two planets are in the no-vedha exception list.", "file_type": "rationale", "source_file": "app/gochara_vedha_engine.py", "source_location": "L95"}, {"id": "gochara_vedha_engine_rationale_109", "label": "For each transit entry, check if another transiting planet occupies the     vedh", "file_type": "rationale", "source_file": "app/gochara_vedha_engine.py", "source_location": "L109"}, {"id": "gochara_vedha_engine_rationale_202", "label": "For each transit entry, compute nakshatra distance from natal Moon nakshatra.", "file_type": "rationale", "source_file": "app/gochara_vedha_engine.py", "source_location": "L202"}, {"id": "gochara_vedha_engine_rationale_282", "label": "Apply Vedha + Latta classical modifiers in sequence.     Returns the enriched tr", "file_type": "rationale", "source_file": "app/gochara_vedha_engine.py", "source_location": "L282"}], "edges": [{"source": "gochara_vedha_engine", "target": "json", "relation": "imports", "confidence": "EXTRACTED", "source_file": "app/gochara_vedha_engine.py", "source_location": "L18", "weight": 1.0}, {"source": "gochara_vedha_engine", "target": "os", "relation": "imports", "confidence": "EXTRACTED", "source_file": "app/gochara_vedha_engine.py", "source_location": "L19", "weight": 1.0}, {"source": "gochara_vedha_engine", "target": "typing", "relation": "imports_from", "confidence": "EXTRACTED", "source_file": "app/gochara_vedha_engine.py", "source_location": "L20", "weight": 1.0}, {"source": "gochara_vedha_engine", "target": "gochara_vedha_engine_load_vedha_table", "relation": "contains", "confidence": "EXTRACTED", "source_file": "app/gochara_vedha_engine.py", "source_location": "L44", "weight": 1.0}, {"source": "gochara_vedha_engine", "target": "gochara_vedha_engine_load_latta_table", "relation": "contains", "confidence": "EXTRACTED", "source_file": "app/gochara_vedha_engine.py", "source_location": "L52", "weight": 1.0}, {"source": "gochara_vedha_engine", "target": "gochara_vedha_engine_house_from_moon", "relation": "contains", "confidence": "EXTRACTED", "source_file": "app/gochara_vedha_engine.py", "source_location": "L64", "weight": 1.0}, {"source": "gochara_vedha_engine", "target": "gochara_vedha_engine_nakshatra_from_longitude", "relation": "contains", "confidence": "EXTRACTED", "source_file": "app/gochara_vedha_engine.py", "source_location": "L74", "weight": 1.0}, {"source": "gochara_vedha_engine", "target": "gochara_vedha_engine_nakshatra_distance", "relation": "contains", "confidence": "EXTRACTED", "source_file": "app/gochara_vedha_engine.py", "source_location": "L84", "weight": 1.0}, {"source": "gochara_vedha_engine", "target": "gochara_vedha_engine_is_exception_pair", "relation": "contains", "confidence": "EXTRACTED", "source_file": "app/gochara_vedha_engine.py", "source_location": "L94", "weight": 1.0}, {"source": "gochara_vedha_engine", "target": "gochara_vedha_engine_apply_vedhas", "relation": "contains", "confidence": "EXTRACTED", "source_file": "app/gochara_vedha_engine.py", "source_location": "L105", "weight": 1.0}, {"source": "gochara_vedha_engine", "target": "gochara_vedha_engine_apply_lattas", "relation": "contains", "confidence": "EXTRACTED", "source_file": "app/gochara_vedha_engine.py", "source_location": "L198", "weight": 1.0}, {"source": "gochara_vedha_engine", "target": "gochara_vedha_engine_enrich_transits", "relation": "contains", "confidence": "EXTRACTED", "source_file": "app/gochara_vedha_engine.py", "source_location": "L278", "weight": 1.0}, {"source": "gochara_vedha_engine_apply_vedhas", "target": "gochara_vedha_engine_load_vedha_table", "relation": "calls", "confidence": "EXTRACTED", "source_file": "app/gochara_vedha_engine.py", "source_location": "L121", "weight": 1.0}, {"source": "gochara_vedha_engine_apply_vedhas", "target": "gochara_vedha_engine_house_from_moon", "relation": "calls", "confidence": "EXTRACTED", "source_file": "app/gochara_vedha_engine.py", "source_location": "L140", "weight": 1.0}, {"source": "gochara_vedha_engine_apply_vedhas", "target": "gochara_vedha_engine_is_exception_pair", "relation": "calls", "confidence": "EXTRACTED", "source_file": "app/gochara_vedha_engine.py", "source_location": "L167", "weight": 1.0}, {"source": "gochara_vedha_engine_apply_lattas", "target": "gochara_vedha_engine_load_latta_table", "relation": "calls", "confidence": "EXTRACTED", "source_file": "app/gochara_vedha_engine.py", "source_location": "L214", "weight": 1.0}, {"source": "gochara_vedha_engine_apply_lattas", "target": "gochara_vedha_engine_nakshatra_from_longitude", "relation": "calls", "confidence": "EXTRACTED", "source_file": "app/gochara_vedha_engine.py", "source_location": "L220", "weight": 1.0}, {"source": "gochara_vedha_engine_apply_lattas", "target": "gochara_vedha_engine_nakshatra_distance", "relation": "calls", "confidence": "EXTRACTED", "source_file": "app/gochara_vedha_engine.py", "source_location": "L245", "weight": 1.0}, {"source": "gochara_vedha_engine_enrich_transits", "target": "gochara_vedha_engine_apply_vedhas", "relation": "calls", "confidence": "EXTRACTED", "source_file": "app/gochara_vedha_engine.py", "source_location": "L286", "weight": 1.0}, {"source": "gochara_vedha_engine_enrich_transits", "target": "gochara_vedha_engine_apply_lattas", "relation": "calls", "confidence": "EXTRACTED", "source_file": "app/gochara_vedha_engine.py", "source_location": "L287", "weight": 1.0}, {"source": "gochara_vedha_engine_rationale_1", "target": "gochara_vedha_engine", "relation": "rationale_for", "confidence": "EXTRACTED", "source_file": "app/gochara_vedha_engine.py", "source_location": "L1", "weight": 1.0}, {"source": "gochara_vedha_engine_rationale_65", "target": "gochara_vedha_engine_house_from_moon", "relation": "rationale_for", "confidence": "EXTRACTED", "source_file": "app/gochara_vedha_engine.py", "source_location": "L65", "weight": 1.0}, {"source": "gochara_vedha_engine_rationale_75", "target": "gochara_vedha_engine_nakshatra_from_longitude", "relation": "rationale_for", "confidence": "EXTRACTED", "source_file": "app/gochara_vedha_engine.py", "source_location": "L75", "weight": 1.0}, {"source": "gochara_vedha_engine_rationale_85", "target": "gochara_vedha_engine_nakshatra_distance", "relation": "rationale_for", "confidence": "EXTRACTED", "source_file": "app/gochara_vedha_engine.py", "source_location": "L85", "weight": 1.0}, {"source": "gochara_vedha_engine_rationale_95", "target": "gochara_vedha_engine_is_exception_pair", "relation": "rationale_for", "confidence": "EXTRACTED", "source_file": "app/gochara_vedha_engine.py", "source_location": "L95", "weight": 1.0}, {"source": "gochara_vedha_engine_rationale_109", "target": "gochara_vedha_engine_apply_vedhas", "relation": "rationale_for", "confidence": "EXTRACTED", "source_file": "app/gochara_vedha_engine.py", "source_location": "L109", "weight": 1.0}, {"source": "gochara_vedha_engine_rationale_202", "target": "gochara_vedha_engine_apply_lattas", "relation": "rationale_for", "confidence": "EXTRACTED", "source_file": "app/gochara_vedha_engine.py", "source_location": "L202", "weight": 1.0}, {"source": "gochara_vedha_engine_rationale_282", "target": "gochara_vedha_engine_enrich_transits", "relation": "rationale_for", "confidence": "EXTRACTED", "source_file": "app/gochara_vedha_engine.py", "source_location": "L282", "weight": 1.0}]}