{"nodes": [{"id": "clientselector_c29be5jo", "label": "ClientSelector-C29Be5JO.js", "file_type": "code", "source_file": "frontend/dist-staging/assets/ClientSelector-C29Be5JO.js", "source_location": "L1"}, {"id": "clientselector_c29be5jo_f", "label": "F()", "file_type": "code", "source_file": "frontend/dist-staging/assets/ClientSelector-C29Be5JO.js", "source_location": "L1"}, {"id": "clientselector_c29be5jo_h", "label": "H()", "file_type": "code", "source_file": "frontend/dist-staging/assets/ClientSelector-C29Be5JO.js", "source_location": "L1"}], "edges": [{"source": "clientselector_c29be5jo", "target": "vendor_ui_wlmbmztc_js", "relation": "imports_from", "confidence": "EXTRACTED", "source_file": "frontend/dist-staging/assets/ClientSelector-C29Be5JO.js", "source_location": "L1", "weight": 1.0}, {"source": "clientselector_c29be5jo", "target": "vendor_react_im6hat6x_js", "relation": "imports_from", "confidence": "EXTRACTED", "source_file": "frontend/dist-staging/assets/ClientSelector-C29Be5JO.js", "source_location": "L1", "weight": 1.0}, {"source": "clientselector_c29be5jo", "target": "index_bbse_ua3_js", "relation": "imports_from", "confidence": "EXTRACTED", "source_file": "frontend/dist-staging/assets/ClientSelector-C29Be5JO.js", "source_location": "L1", "weight": 1.0}, {"source": "clientselector_c29be5jo", "target": "search_djgr9m5q_js", "relation": "imports_from", "confidence": "EXTRACTED", "source_file": "frontend/dist-staging/assets/ClientSelector-C29Be5JO.js", "source_location": "L1", "weight": 1.0}, {"source": "clientselector_c29be5jo", "target": "loader_circle_cikhqraw_js", "relation": "imports_from", "confidence": "EXTRACTED", "source_file": "frontend/dist-staging/assets/ClientSelector-C29Be5JO.js", "source_location": "L1", "weight": 1.0}, {"source": "clientselector_c29be5jo", "target": "clientselector_c29be5jo_f", "relation": "contains", "confidence": "EXTRACTED", "source_file": "frontend/dist-staging/assets/ClientSelector-C29Be5JO.js", "source_location": "L1", "weight": 1.0}, {"source": "clientselector_c29be5jo", "target": "clientselector_c29be5jo_h", "relation": "contains", "confidence": "EXTRACTED", "source_file": "frontend/dist-staging/assets/ClientSelector-C29Be5JO.js", "source_location": "L1", "weight": 1.0}]}