{"nodes": [{"id": "test_numerology", "label": "test_numerology.py", "file_type": "code", "source_file": "tests/test_numerology.py", "source_location": "L1"}, {"id": "test_numerology_test_life_path_basic", "label": "test_life_path_basic()", "file_type": "code", "source_file": "tests/test_numerology.py", "source_location": "L5"}, {"id": "test_numerology_test_life_path_master_number_11", "label": "test_life_path_master_number_11()", "file_type": "code", "source_file": "tests/test_numerology.py", "source_location": "L13"}, {"id": "test_numerology_test_destiny_number", "label": "test_destiny_number()", "file_type": "code", "source_file": "tests/test_numerology.py", "source_location": "L23"}, {"id": "test_numerology_test_soul_urge_vowels_only", "label": "test_soul_urge_vowels_only()", "file_type": "code", "source_file": "tests/test_numerology.py", "source_location": "L31"}, {"id": "test_numerology_test_personality_consonants_only", "label": "test_personality_consonants_only()", "file_type": "code", "source_file": "tests/test_numerology.py", "source_location": "L43"}, {"id": "test_numerology_test_return_structure", "label": "test_return_structure()", "file_type": "code", "source_file": "tests/test_numerology.py", "source_location": "L50"}, {"id": "test_numerology_test_reduce_master_numbers_preserved", "label": "test_reduce_master_numbers_preserved()", "file_type": "code", "source_file": "tests/test_numerology.py", "source_location": "L67"}, {"id": "test_numerology_test_invalid_date_format", "label": "test_invalid_date_format()", "file_type": "code", "source_file": "tests/test_numerology.py", "source_location": "L76"}, {"id": "test_numerology_rationale_1", "label": "Tests for numerology_engine.py \u2014 Pythagorean numerology calculations.", "file_type": "rationale", "source_file": "tests/test_numerology.py", "source_location": "L1"}, {"id": "test_numerology_rationale_6", "label": "Life path for 1990-01-15: 1+9+9+0=19->10->1 + 0+1=1 + 1+5=6 => 1+1+6=8.", "file_type": "rationale", "source_file": "tests/test_numerology.py", "source_location": "L6"}, {"id": "test_numerology_rationale_14", "label": "Verify master number 11 is preserved (not reduced to 2).", "file_type": "rationale", "source_file": "tests/test_numerology.py", "source_location": "L14"}, {"id": "test_numerology_rationale_24", "label": "Destiny number (formerly expression) uses all letters of the name.", "file_type": "rationale", "source_file": "tests/test_numerology.py", "source_location": "L24"}, {"id": "test_numerology_rationale_32", "label": "Soul urge uses only vowels (A, E, I, O, U).", "file_type": "rationale", "source_file": "tests/test_numerology.py", "source_location": "L32"}, {"id": "test_numerology_rationale_44", "label": "Personality uses only consonants.", "file_type": "rationale", "source_file": "tests/test_numerology.py", "source_location": "L44"}, {"id": "test_numerology_rationale_51", "label": "Verify all required keys are present in the output dict.", "file_type": "rationale", "source_file": "tests/test_numerology.py", "source_location": "L51"}, {"id": "test_numerology_rationale_68", "label": "Master numbers 11, 22, 33 should not be reduced further.", "file_type": "rationale", "source_file": "tests/test_numerology.py", "source_location": "L68"}, {"id": "test_numerology_rationale_77", "label": "Invalid date format raises ValueError.", "file_type": "rationale", "source_file": "tests/test_numerology.py", "source_location": "L77"}], "edges": [{"source": "test_numerology", "target": "pytest", "relation": "imports", "confidence": "EXTRACTED", "source_file": "tests/test_numerology.py", "source_location": "L2", "weight": 1.0}, {"source": "test_numerology", "target": "test_numerology_test_life_path_basic", "relation": "contains", "confidence": "EXTRACTED", "source_file": "tests/test_numerology.py", "source_location": "L5", "weight": 1.0}, {"source": "test_numerology", "target": "test_numerology_test_life_path_master_number_11", "relation": "contains", "confidence": "EXTRACTED", "source_file": "tests/test_numerology.py", "source_location": "L13", "weight": 1.0}, {"source": "test_numerology", "target": "test_numerology_test_destiny_number", "relation": "contains", "confidence": "EXTRACTED", "source_file": "tests/test_numerology.py", "source_location": "L23", "weight": 1.0}, {"source": "test_numerology", "target": "test_numerology_test_soul_urge_vowels_only", "relation": "contains", "confidence": "EXTRACTED", "source_file": "tests/test_numerology.py", "source_location": "L31", "weight": 1.0}, {"source": "test_numerology", "target": "test_numerology_test_personality_consonants_only", "relation": "contains", "confidence": "EXTRACTED", "source_file": "tests/test_numerology.py", "source_location": "L43", "weight": 1.0}, {"source": "test_numerology", "target": "test_numerology_test_return_structure", "relation": "contains", "confidence": "EXTRACTED", "source_file": "tests/test_numerology.py", "source_location": "L50", "weight": 1.0}, {"source": "test_numerology", "target": "test_numerology_test_reduce_master_numbers_preserved", "relation": "contains", "confidence": "EXTRACTED", "source_file": "tests/test_numerology.py", "source_location": "L67", "weight": 1.0}, {"source": "test_numerology", "target": "test_numerology_test_invalid_date_format", "relation": "contains", "confidence": "EXTRACTED", "source_file": "tests/test_numerology.py", "source_location": "L76", "weight": 1.0}, {"source": "test_numerology_rationale_1", "target": "test_numerology", "relation": "rationale_for", "confidence": "EXTRACTED", "source_file": "tests/test_numerology.py", "source_location": "L1", "weight": 1.0}, {"source": "test_numerology_rationale_6", "target": "test_numerology_test_life_path_basic", "relation": "rationale_for", "confidence": "EXTRACTED", "source_file": "tests/test_numerology.py", "source_location": "L6", "weight": 1.0}, {"source": "test_numerology_rationale_14", "target": "test_numerology_test_life_path_master_number_11", "relation": "rationale_for", "confidence": "EXTRACTED", "source_file": "tests/test_numerology.py", "source_location": "L14", "weight": 1.0}, {"source": "test_numerology_rationale_24", "target": "test_numerology_test_destiny_number", "relation": "rationale_for", "confidence": "EXTRACTED", "source_file": "tests/test_numerology.py", "source_location": "L24", "weight": 1.0}, {"source": "test_numerology_rationale_32", "target": "test_numerology_test_soul_urge_vowels_only", "relation": "rationale_for", "confidence": "EXTRACTED", "source_file": "tests/test_numerology.py", "source_location": "L32", "weight": 1.0}, {"source": "test_numerology_rationale_44", "target": "test_numerology_test_personality_consonants_only", "relation": "rationale_for", "confidence": "EXTRACTED", "source_file": "tests/test_numerology.py", "source_location": "L44", "weight": 1.0}, {"source": "test_numerology_rationale_51", "target": "test_numerology_test_return_structure", "relation": "rationale_for", "confidence": "EXTRACTED", "source_file": "tests/test_numerology.py", "source_location": "L51", "weight": 1.0}, {"source": "test_numerology_rationale_68", "target": "test_numerology_test_reduce_master_numbers_preserved", "relation": "rationale_for", "confidence": "EXTRACTED", "source_file": "tests/test_numerology.py", "source_location": "L68", "weight": 1.0}, {"source": "test_numerology_rationale_77", "target": "test_numerology_test_invalid_date_format", "relation": "rationale_for", "confidence": "EXTRACTED", "source_file": "tests/test_numerology.py", "source_location": "L77", "weight": 1.0}]}