{"nodes": [{"id": "panchang", "label": "panchang.py", "file_type": "code", "source_file": "app/routes/panchang.py", "source_location": "L1"}, {"id": "panchang_today", "label": "_today()", "file_type": "code", "source_file": "app/routes/panchang.py", "source_location": "L103"}, {"id": "panchang_parse_date", "label": "_parse_date()", "file_type": "code", "source_file": "app/routes/panchang.py", "source_location": "L107"}, {"id": "panchang_get_panchang", "label": "get_panchang()", "file_type": "code", "source_file": "app/routes/panchang.py", "source_location": "L123"}, {"id": "panchang_get_monthly_panchang", "label": "get_monthly_panchang()", "file_type": "code", "source_file": "app/routes/panchang.py", "source_location": "L249"}, {"id": "panchang_get_choghadiya", "label": "get_choghadiya()", "file_type": "code", "source_file": "app/routes/panchang.py", "source_location": "L340"}, {"id": "panchang_get_muhurat", "label": "get_muhurat()", "file_type": "code", "source_file": "app/routes/panchang.py", "source_location": "L366"}, {"id": "panchang_get_sunrise", "label": "get_sunrise()", "file_type": "code", "source_file": "app/routes/panchang.py", "source_location": "L440"}, {"id": "panchang_list_festivals", "label": "list_festivals()", "file_type": "code", "source_file": "app/routes/panchang.py", "source_location": "L460"}, {"id": "panchang_find_hindi_font", "label": "_find_hindi_font()", "file_type": "code", "source_file": "app/routes/panchang.py", "source_location": "L494"}, {"id": "panchang_build_panchang_pdf", "label": "_build_panchang_pdf()", "file_type": "code", "source_file": "app/routes/panchang.py", "source_location": "L508"}, {"id": "panchang_download_panchang_pdf", "label": "download_panchang_pdf()", "file_type": "code", "source_file": "app/routes/panchang.py", "source_location": "L728"}, {"id": "panchang_cleanup_panchang_cache", "label": "cleanup_panchang_cache()", "file_type": "code", "source_file": "app/routes/panchang.py", "source_location": "L761"}, {"id": "panchang_rationale_1", "label": "Panchang routes \u2014 daily panchang, choghadiya, muhurat, sunrise, festivals, month", "file_type": "rationale", "source_file": "app/routes/panchang.py", "source_location": "L1"}, {"id": "panchang_rationale_108", "label": "Parse a date string, raising HTTPException on invalid format.", "file_type": "rationale", "source_file": "app/routes/panchang.py", "source_location": "L108"}, {"id": "panchang_rationale_129", "label": "Calculate complete Panchang for a given date and location.", "file_type": "rationale", "source_file": "app/routes/panchang.py", "source_location": "L129"}, {"id": "panchang_rationale_256", "label": "Get panchang summary for each day of a month.", "file_type": "rationale", "source_file": "app/routes/panchang.py", "source_location": "L256"}, {"id": "panchang_rationale_345", "label": "Calculate Choghadiya (auspicious time periods) for the day.", "file_type": "rationale", "source_file": "app/routes/panchang.py", "source_location": "L345"}, {"id": "panchang_rationale_374", "label": "Get auspicious muhurat dates for a given type and period.", "file_type": "rationale", "source_file": "app/routes/panchang.py", "source_location": "L374"}, {"id": "panchang_rationale_445", "label": "Get sunrise, sunset, moonrise, moonset for a given date and location.", "file_type": "rationale", "source_file": "app/routes/panchang.py", "source_location": "L445"}, {"id": "panchang_rationale_465", "label": "List festivals for a given year, optionally filtered by category.", "file_type": "rationale", "source_file": "app/routes/panchang.py", "source_location": "L465"}, {"id": "panchang_rationale_495", "label": "Locate a Devanagari-capable TTF font on disk.", "file_type": "rationale", "source_file": "app/routes/panchang.py", "source_location": "L495"}, {"id": "panchang_rationale_509", "label": "Build a clean single-page Panchang summary PDF (like WhatsApp text style).", "file_type": "rationale", "source_file": "app/routes/panchang.py", "source_location": "L509"}, {"id": "panchang_rationale_733", "label": "Generate and download a bilingual Hindi+English Panchang PDF report.", "file_type": "rationale", "source_file": "app/routes/panchang.py", "source_location": "L733"}, {"id": "panchang_rationale_765", "label": "Remove panchang cache entries older than max_age_days.     Requires admin privil", "file_type": "rationale", "source_file": "app/routes/panchang.py", "source_location": "L765"}], "edges": [{"source": "panchang", "target": "io", "relation": "imports", "confidence": "EXTRACTED", "source_file": "app/routes/panchang.py", "source_location": "L2", "weight": 1.0}, {"source": "panchang", "target": "json", "relation": "imports", "confidence": "EXTRACTED", "source_file": "app/routes/panchang.py", "source_location": "L3", "weight": 1.0}, {"source": "panchang", "target": "os", "relation": "imports", "confidence": "EXTRACTED", "source_file": "app/routes/panchang.py", "source_location": "L4", "weight": 1.0}, {"source": "panchang", "target": "calendar", "relation": "imports", "confidence": "EXTRACTED", "source_file": "app/routes/panchang.py", "source_location": "L5", "weight": 1.0}, {"source": "panchang", "target": "typing", "relation": "imports_from", "confidence": "EXTRACTED", "source_file": "app/routes/panchang.py", "source_location": "L6", "weight": 1.0}, {"source": "panchang", "target": "datetime", "relation": "imports_from", "confidence": "EXTRACTED", "source_file": "app/routes/panchang.py", "source_location": "L7", "weight": 1.0}, {"source": "panchang", "target": "fastapi", "relation": "imports_from", "confidence": "EXTRACTED", "source_file": "app/routes/panchang.py", "source_location": "L9", "weight": 1.0}, {"source": "panchang", "target": "fastapi_responses", "relation": "imports_from", "confidence": "EXTRACTED", "source_file": "app/routes/panchang.py", "source_location": "L10", "weight": 1.0}, {"source": "panchang", "target": "app_database", "relation": "imports_from", "confidence": "EXTRACTED", "source_file": "app/routes/panchang.py", "source_location": "L12", "weight": 1.0}, {"source": "panchang", "target": "app_panchang_engine", "relation": "imports_from", "confidence": "EXTRACTED", "source_file": "app/routes/panchang.py", "source_location": "L13", "weight": 1.0}, {"source": "panchang", "target": "app_festival_engine", "relation": "imports_from", "confidence": "EXTRACTED", "source_file": "app/routes/panchang.py", "source_location": "L18", "weight": 1.0}, {"source": "panchang", "target": "panchang_today", "relation": "contains", "confidence": "EXTRACTED", "source_file": "app/routes/panchang.py", "source_location": "L103", "weight": 1.0}, {"source": "panchang", "target": "panchang_parse_date", "relation": "contains", "confidence": "EXTRACTED", "source_file": "app/routes/panchang.py", "source_location": "L107", "weight": 1.0}, {"source": "panchang", "target": "panchang_get_panchang", "relation": "contains", "confidence": "EXTRACTED", "source_file": "app/routes/panchang.py", "source_location": "L123", "weight": 1.0}, {"source": "panchang", "target": "panchang_get_monthly_panchang", "relation": "contains", "confidence": "EXTRACTED", "source_file": "app/routes/panchang.py", "source_location": "L249", "weight": 1.0}, {"source": "panchang", "target": "panchang_get_choghadiya", "relation": "contains", "confidence": "EXTRACTED", "source_file": "app/routes/panchang.py", "source_location": "L340", "weight": 1.0}, {"source": "panchang", "target": "panchang_get_muhurat", "relation": "contains", "confidence": "EXTRACTED", "source_file": "app/routes/panchang.py", "source_location": "L366", "weight": 1.0}, {"source": "panchang", "target": "panchang_get_sunrise", "relation": "contains", "confidence": "EXTRACTED", "source_file": "app/routes/panchang.py", "source_location": "L440", "weight": 1.0}, {"source": "panchang", "target": "panchang_list_festivals", "relation": "contains", "confidence": "EXTRACTED", "source_file": "app/routes/panchang.py", "source_location": "L460", "weight": 1.0}, {"source": "panchang", "target": "panchang_find_hindi_font", "relation": "contains", "confidence": "EXTRACTED", "source_file": "app/routes/panchang.py", "source_location": "L494", "weight": 1.0}, {"source": "panchang", "target": "panchang_build_panchang_pdf", "relation": "contains", "confidence": "EXTRACTED", "source_file": "app/routes/panchang.py", "source_location": "L508", "weight": 1.0}, {"source": "panchang", "target": "panchang_download_panchang_pdf", "relation": "contains", "confidence": "EXTRACTED", "source_file": "app/routes/panchang.py", "source_location": "L728", "weight": 1.0}, {"source": "panchang", "target": "panchang_cleanup_panchang_cache", "relation": "contains", "confidence": "EXTRACTED", "source_file": "app/routes/panchang.py", "source_location": "L761", "weight": 1.0}, {"source": "panchang_get_panchang", "target": "panchang_today", "relation": "calls", "confidence": "EXTRACTED", "source_file": "app/routes/panchang.py", "source_location": "L130", "weight": 1.0}, {"source": "panchang_get_panchang", "target": "panchang_parse_date", "relation": "calls", "confidence": "EXTRACTED", "source_file": "app/routes/panchang.py", "source_location": "L131", "weight": 1.0}, {"source": "panchang_get_choghadiya", "target": "panchang_today", "relation": "calls", "confidence": "EXTRACTED", "source_file": "app/routes/panchang.py", "source_location": "L346", "weight": 1.0}, {"source": "panchang_get_choghadiya", "target": "panchang_parse_date", "relation": "calls", "confidence": "EXTRACTED", "source_file": "app/routes/panchang.py", "source_location": "L347", "weight": 1.0}, {"source": "panchang_get_sunrise", "target": "panchang_today", "relation": "calls", "confidence": "EXTRACTED", "source_file": "app/routes/panchang.py", "source_location": "L446", "weight": 1.0}, {"source": "panchang_get_sunrise", "target": "panchang_parse_date", "relation": "calls", "confidence": "EXTRACTED", "source_file": "app/routes/panchang.py", "source_location": "L447", "weight": 1.0}, {"source": "panchang_build_panchang_pdf", "target": "panchang_find_hindi_font", "relation": "calls", "confidence": "EXTRACTED", "source_file": "app/routes/panchang.py", "source_location": "L517", "weight": 1.0}, {"source": "panchang_download_panchang_pdf", "target": "panchang_parse_date", "relation": "calls", "confidence": "EXTRACTED", "source_file": "app/routes/panchang.py", "source_location": "L735", "weight": 1.0}, {"source": "panchang_download_panchang_pdf", "target": "panchang_build_panchang_pdf", "relation": "calls", "confidence": "EXTRACTED", "source_file": "app/routes/panchang.py", "source_location": "L750", "weight": 1.0}, {"source": "panchang_rationale_1", "target": "panchang", "relation": "rationale_for", "confidence": "EXTRACTED", "source_file": "app/routes/panchang.py", "source_location": "L1", "weight": 1.0}, {"source": "panchang_rationale_108", "target": "panchang_parse_date", "relation": "rationale_for", "confidence": "EXTRACTED", "source_file": "app/routes/panchang.py", "source_location": "L108", "weight": 1.0}, {"source": "panchang_rationale_129", "target": "panchang_get_panchang", "relation": "rationale_for", "confidence": "EXTRACTED", "source_file": "app/routes/panchang.py", "source_location": "L129", "weight": 1.0}, {"source": "panchang_rationale_256", "target": "panchang_get_monthly_panchang", "relation": "rationale_for", "confidence": "EXTRACTED", "source_file": "app/routes/panchang.py", "source_location": "L256", "weight": 1.0}, {"source": "panchang_rationale_345", "target": "panchang_get_choghadiya", "relation": "rationale_for", "confidence": "EXTRACTED", "source_file": "app/routes/panchang.py", "source_location": "L345", "weight": 1.0}, {"source": "panchang_rationale_374", "target": "panchang_get_muhurat", "relation": "rationale_for", "confidence": "EXTRACTED", "source_file": "app/routes/panchang.py", "source_location": "L374", "weight": 1.0}, {"source": "panchang_rationale_445", "target": "panchang_get_sunrise", "relation": "rationale_for", "confidence": "EXTRACTED", "source_file": "app/routes/panchang.py", "source_location": "L445", "weight": 1.0}, {"source": "panchang_rationale_465", "target": "panchang_list_festivals", "relation": "rationale_for", "confidence": "EXTRACTED", "source_file": "app/routes/panchang.py", "source_location": "L465", "weight": 1.0}, {"source": "panchang_rationale_495", "target": "panchang_find_hindi_font", "relation": "rationale_for", "confidence": "EXTRACTED", "source_file": "app/routes/panchang.py", "source_location": "L495", "weight": 1.0}, {"source": "panchang_rationale_509", "target": "panchang_build_panchang_pdf", "relation": "rationale_for", "confidence": "EXTRACTED", "source_file": "app/routes/panchang.py", "source_location": "L509", "weight": 1.0}, {"source": "panchang_rationale_733", "target": "panchang_download_panchang_pdf", "relation": "rationale_for", "confidence": "EXTRACTED", "source_file": "app/routes/panchang.py", "source_location": "L733", "weight": 1.0}, {"source": "panchang_rationale_765", "target": "panchang_cleanup_panchang_cache", "relation": "rationale_for", "confidence": "EXTRACTED", "source_file": "app/routes/panchang.py", "source_location": "L765", "weight": 1.0}]}